llm_society/__init__.py
llm_society/api.py
llm_society/cli.py
llm_society/config.py
llm_society/dashboard.py
llm_society/llm.py
llm_society/network.py
llm_society/persona.py
llm_society/simulation.py
llm_society/viz.py
llm_society/data/example.yaml
llm_society-0.3.2.dist-info/licenses/LICENSE
llm_society-0.3.2.dist-info/METADATA
llm_society-0.3.2.dist-info/WHEEL
llm_society-0.3.2.dist-info/entry_points.txt
llm_society-0.3.2.dist-info/top_level.txt
llm_society-0.3.2.dist-info/RECORD
