Metadata-Version: 2.4
Name: llm-society
Version: 0.3.2
Summary: LLM-driven agent-based information diffusion simulation
Author-email: Tianzhu Qin <tianzhu@stanford.edu>
License: MIT
Project-URL: Homepage, https://github.com/TianzhuQin/LLM-ABM-Information-Network
Project-URL: Repository, https://github.com/TianzhuQin/LLM-ABM-Information-Network.git
Project-URL: Issues, https://github.com/TianzhuQin/LLM-ABM-Information-Network/issues
Keywords: agent-based,simulation,llm,information,diffusion,networks
Classifier: Programming Language :: Python :: 3
Classifier: License :: OSI Approved :: MIT License
Classifier: Operating System :: OS Independent
Requires-Python: >=3.10
License-File: LICENSE
Requires-Dist: openai>=1.14.0
Requires-Dist: numpy>=1.24.0
Requires-Dist: pandas>=2.0.0
Requires-Dist: networkx>=3.1
Requires-Dist: matplotlib>=3.7.0
Requires-Dist: pyyaml>=6.0.0
Requires-Dist: plotly>=5.18.0
Requires-Dist: bokeh>=3.3.0
Dynamic: license-file
